MANIFEST.in
requirements.txt
setup.cfg
setup.py
pyEOS/__init__.py
pyEOS/eos.py
pyEOS/exceptions.py
pyEOS.egg-info/PKG-INFO
pyEOS.egg-info/SOURCES.txt
pyEOS.egg-info/dependency_links.txt
pyEOS.egg-info/requires.txt
pyEOS.egg-info/top_level.txt