Metadata-Version: 1.1
Name: pyEOS
Version: 0.62
Summary: Python API to interact with network devices running EOS
Home-page: https://github.com/spotify/pyeos/
Author: David Barroso
Author-email: dbarroso@spotify.com
License: UNKNOWN
Download-URL: https://github.com/spotify/pyeos/tarball/0.62
Keywords: EOS,networking
Platform: UNKNOWN
